CHANGES
LICENSE
MANIFEST.in
README
setup.py
pystacia/__init__.py
pystacia/color.py
pystacia/compat.py
pystacia/image.py
pystacia/lazyenum.py
pystacia/magick.py
pystacia/util.py
pystacia.egg-info/PKG-INFO
pystacia.egg-info/SOURCES.txt
pystacia.egg-info/dependency_links.txt
pystacia.egg-info/requires.txt
pystacia.egg-info/top_level.txt
pystacia/api/__init__.py
pystacia/api/enum.py
pystacia/api/func.py
pystacia/api/type.py
pystacia/api/tests/__init__.py
pystacia/api/tests/enum_tests.py
pystacia/api/tests/func_tests.py
pystacia/tests/__init__.py
pystacia/tests/color_tests.py
pystacia/tests/compat_tests.py
pystacia/tests/image_tests.py
pystacia/tests/lazyenum_tests.py
pystacia/tests/magick_tests.py
pystacia/tests/util_tests.py