Metadata-Version: 1.0
Name: pystacia
Version: 0.1beta
Summary: Python raster imaging library
Home-page: http://liquibits.bitbucket.org/
Author: Paweł Piotr Przeradowski
Author-email: przeradowski@gmail.com
License: MIT License
Platform: UNKNOWN
Classifier: Development Status :: 4 - Beta
Classifier: Intended Audience :: Developers
Classifier: License :: OSI Approved :: MIT License
Classifier: Operating System :: POSIX :: Linux
Classifier: Operating System :: MacOS :: MacOS X
Classifier: Operating System :: Microsoft :: Windows
Classifier: Operating System :: POSIX
Classifier: Programming Language :: Python
Classifier: Programming Language :: Python :: 3
Classifier: Topic :: Multimedia :: Graphics
